cubicweb_keyword/__init__.py
cubicweb_keyword/__pkginfo__.py
cubicweb_keyword/entities.py
cubicweb_keyword/hooks.py
cubicweb_keyword/schema.py
cubicweb_keyword/sobjects.py
cubicweb_keyword/views.py
cubicweb_keyword/data/cubes.keyword.js
cubicweb_keyword/doc/schema.png
cubicweb_keyword/doc/screenshot_keyword_tree.png
cubicweb_keyword/i18n/en.po
cubicweb_keyword/i18n/fr.po
cubicweb_keyword/migration/1.0.2_Any.py
cubicweb_keyword/migration/1.4.0_Any.py
cubicweb_keyword/migration/postcreate.py
cubicweb_keyword-4.0.0.dist-info/METADATA
cubicweb_keyword-4.0.0.dist-info/WHEEL
cubicweb_keyword-4.0.0.dist-info/entry_points.txt
cubicweb_keyword-4.0.0.dist-info/top_level.txt
cubicweb_keyword-4.0.0.dist-info/RECORD
