Metadata-Version: 2.1
Name: cubicweb-keyword
Version: 4.0.0
Summary: classification schemes system for the Cubicweb framework
Home-page: https://forge.extranet.logilab.fr/cubicweb/cubes/cubicweb-keyword
Author: Logilab
Author-email: contact@logilab.fr
License: LGPL
Classifier: Environment :: Web Environment
Classifier: Framework :: CubicWeb
Classifier: Programming Language :: Python
Classifier: Programming Language :: JavaScript
Requires-Dist: cubicweb (<5.0.0,>=4.0.0)
Requires-Dist: cubicweb-web (<2.0.0,>=1.0.0)
